Metadata-Version: 2.1
Name: RiboParser
Version: 0.1.7.7
Summary: A pipeline for ribosome profiling data analysis
Home-page: https://github.com/renscq/RiboParser
Author: Ren Shuchao
Author-email: rensc0718@163.com
License: GPL
Platform: linux-x86_64
Classifier: Programming Language :: Python :: 3.12
Classifier: Operating System :: POSIX :: Linux
Classifier: Topic :: Scientific/Engineering :: Bio-Informatics
Classifier: Intended Audience :: Science/Research
Requires-Python: >=3.12
Requires-Dist: numpy ~=1.26.4
Requires-Dist: pandas ~=2.2.2
Requires-Dist: pyarrow ~=16.1.0
Requires-Dist: polars ~=0.20.31
Requires-Dist: biopython ~=1.78
Requires-Dist: scipy ~=1.12.0
Requires-Dist: scikit-learn ~=1.4.2
Requires-Dist: statsmodels ~=0.14.2
Requires-Dist: pysam ~=0.22.1
Requires-Dist: joblib ~=1.4.2
Requires-Dist: interval ~=1.0.0
Requires-Dist: matplotlib ~=3.8.4
Requires-Dist: matplotlib-venn ~=1.1.1
Requires-Dist: seaborn ~=0.13.2
Requires-Dist: plotly ~=5.22.0
Requires-Dist: seqlogo ~=5.29.9
Requires-Dist: kaleido ~=0.2.1
